nbagent/__init__.py
nbagent/main.py
nbagent-1.1.0.dist-info/LICENSE
nbagent-1.1.0.dist-info/METADATA
nbagent-1.1.0.dist-info/WHEEL
nbagent-1.1.0.dist-info/entry_points.txt
nbagent-1.1.0.dist-info/top_level.txt
nbagent-1.1.0.dist-info/RECORD
