Metadata-Version: 2.2
Name: nbagent
Version: 1.1.0
Summary: A Nullboard backup agent for Unix systems
Author-email: Luis Medel <luis@luismedel.com>
Project-URL: Homepage, https://github.com/luismedel/nbagent
Classifier: Programming Language :: Python :: 3.8
Classifier: License :: OSI Approved :: MIT License
Classifier: Operating System :: Unix
Classifier: Topic :: System :: Archiving :: Backup
Classifier: Topic :: Utilities
Requires-Python: >=3.8
License-File: LICENSE
Requires-Dist: click==8.1.7
Requires-Dist: Flask==2.3.3
Requires-Dist: Flask-Cors==4.0.0
